cookidoo_api/__init__.py
cookidoo_api/const.py
cookidoo_api/cookidoo.py
cookidoo_api/exceptions.py
cookidoo_api/helpers.py
cookidoo_api/localization.json
cookidoo_api/py.typed
cookidoo_api/raw_types.py
cookidoo_api/types.py
cookidoo_api-0.16.0.dist-info/licenses/LICENSE
cookidoo_api-0.16.0.dist-info/METADATA
cookidoo_api-0.16.0.dist-info/WHEEL
cookidoo_api-0.16.0.dist-info/top_level.txt
cookidoo_api-0.16.0.dist-info/RECORD
