Metadata-Version: 2.4
Name: cookidoo-api
Version: 0.16.0
Summary: Unofficial package to access Cookidoo.
Author-email: Cyrill Raccaud <cyrill.raccaud+pypi@gmail.com>
License-Expression: MIT
Project-URL: Documentation, https://miaucl.github.io/cookidoo-api/
Project-URL: Source, https://github.com/miaucl/cookidoo-api
Project-URL: Issues, https://github.com/miaucl/cookidoo-api/issues
Project-URL: Release notes, https://github.com/miaucl/cookidoo-api/releases
Keywords: cookidoo,todo,home-assistant,iot
Classifier: Programming Language :: Python :: 3
Classifier: Operating System :: OS Independent
Classifier: Intended Audience :: Information Technology
Classifier: Topic :: System :: Monitoring
Classifier: Topic :: System :: Logging
Classifier: Topic :: System :: Systems Administration
Requires-Python: >=3.12
License-File: LICENSE
Requires-Dist: aiohttp
Requires-Dist: aiofiles
Requires-Dist: isodate
Dynamic: license-file
